tarot/__init__.py
tarot/bot_pb2.py
tarot/bot_pb2.pyi
tarot/bot_pb2_grpc.py
tarot/bots_master_pb2.py
tarot/bots_master_pb2.pyi
tarot/bots_master_pb2_grpc.py
tarot/chats_pb2.py
tarot/chats_pb2.pyi
tarot/chats_pb2_grpc.py
tarot/spread_pb2.py
tarot/spread_pb2.pyi
tarot/spread_pb2_grpc.py
tarot/task_pb2.py
tarot/task_pb2.pyi
tarot/task_pb2_grpc.py
tarot/users_pb2.py
tarot/users_pb2.pyi
tarot/users_pb2_grpc.py
tarot/validation_pb2.py
tarot/validation_pb2.pyi
tarot/validation_pb2_grpc.py
tarot_contracts-1.0.13.dist-info/METADATA
tarot_contracts-1.0.13.dist-info/WHEEL
tarot_contracts-1.0.13.dist-info/top_level.txt
tarot_contracts-1.0.13.dist-info/RECORD
