Metadata-Version: 2.1
Name: tarot-contracts
Version: 1.0.13
Summary: A package with gRPC generated code
Author: Vlad Balabash
Author-email: <vladb951@gmail.com>
Keywords: python,grpc,tarotbot
Classifier: Development Status :: 1 - Planning
Classifier: Intended Audience :: Developers
Classifier: Programming Language :: Python :: 3
Classifier: Operating System :: MacOS :: MacOS X
Classifier: Operating System :: Microsoft :: Windows
